catime/__init__.py
catime/cli.py
catime-0.3.0.dist-info/METADATA
catime-0.3.0.dist-info/WHEEL
catime-0.3.0.dist-info/entry_points.txt
catime-0.3.0.dist-info/licenses/LICENSE
catime-0.3.0.dist-info/RECORD
