Metadata-Version: 2.4
Name: catime
Version: 0.3.0
Summary: AI-generated hourly cat images - a new cat every hour!
License-Expression: MIT
License-File: LICENSE
Requires-Python: >=3.10
Requires-Dist: httpx
